{
  "original_approach": {
    "file_category": "IT_SOFTWARE",
    "category_metrics": {
      "input_tokens": 1356,
      "output_tokens": 3,
      "execution_time": 0.3332827091217041,
      "cost": 0.000137
    },
    "knots_metrics": {
      "input_tokens": 1679,
      "output_tokens": 976,
      "execution_time": 2.8139517307281494,
      "cost": 0.000558
    },
    "total_metrics": {
      "input_tokens": 3035,
      "output_tokens": 979,
      "total_tokens": 4014,
      "cost": 0.000695,
      "execution_time": 3.164712905883789
    },
    "category_result": "IT_SOFTWARE",
    "knots_result": "{\n    \"category\": \"it_and_software\",\n    \"extracted_data\": {\n        \"software_info\": {\n            \"name\": \"Nimbus\",\n            \"version\": \"4.2.1\"\n        },\n        \"installation_setup\": {\n            \"steps\": [\n                \"curl -sSL https://nimbus.sh/install.sh | bash\",\n                \"Run post-install verification: nimbus check --all\",\n                \"Generate config scaffold: nimbus init\",\n                \"Edit nimbus.yaml for cluster-specific params\",\n                \"Use nimbus deploy to roll out the control plane\"\n            ],\n            \"configuration\": {\n                \"environment_variables\": [\n                    \"NIMBUS_ENV=production\",\n                    \"NIMBUS_ENABLE_TLS=true\",\n                    \"NIMBUS_API_KEY=[token]\"\n                ],\n                \"dependencies\": [\n                    \"Docker 23+\",\n                    \"Python 3.10+\",\n                    \"Postgres 14\"\n                ]\n            }\n        },\n        \"user_interface_features\": {\n            \"functionalities\": [\n                \"Drag-and-drop service dependency mapping\",\n                \"Live mesh traffic inspection\",\n                \"Alerting & autoscaling rules\",\n                \"Inline YAML editor for resource definitions\",\n                \"Native integrations: GitHub, Datadog, PagerDuty\"\n            ],\n            \"shortcuts\": [\n                \"Ctrl+Shift+F \u2013 Toggle dark mode\",\n                \"Cmd+/ \u2013 Command palette\",\n                \"Esc \u2013 Collapse side navigation\",\n                \"/logs \u2013 Direct log stream via web\"\n            ],\n            \"compatibility\": {\n                \"operating_systems\": [\n                    \"Ubuntu 20.04+\",\n                    \"Amazon Linux 2\",\n                    \"RedHat 8\"\n                ],\n                \"browsers\": [\n                    \"Chrome 118+\",\n                    \"Firefox ESR\"\n                ],\n                \"platforms\": [\n                    \"Kubernetes 1.24\u20131.28\",\n                    \"Istio 1.17+\",\n                    \"Terraform integration supported via plugin\"\n                ]\n            }\n        },\n        \"api_documentation\": {\n            \"endpoints\": [\n                \"GET /clusters/\",\n                \"POST /deployments/\",\n                \"GET /services/{id}\",\n                \"DELETE /nodes/{id}\"\n            ],\n            \"authentication\": [\n                \"OAuth2 with Bearer tokens\",\n                \"API key header (X-Nimbus-Token)\"\n            ],\n            \"code_examples\": \"import requests\\n\\nheaders = {\\\"X-Nimbus-Token\\\": \\\"your_token_here\\\"}\\nresponse = requests.get(\\\"https://api.nimbus.sh/v1/clusters/\\\", headers=headers)\\nprint(response.json())\"\n        },\n        \"security_guidelines\": {\n            \"encryption\": [\n                \"TLS v1.3 enforced\",\n                \"Passwords hashed with Argon2id\",\n                \"Encrypted volumes for audit logs (AES-256)\"\n            ],\n            \"compliance_policies\": [\n                \"JWT sessions expire every 12h; token refresh available\",\n                \"All logs shipped securely via Fluent Bit over gRPC\",\n                \"Admin privileges are scoped with RBAC + time-limited elevation (just-in-time access via Vault)\",\n                \"All PRs undergo static analysis (SonarCloud, Bandit)\",\n                \"No hardcoded credentials; use secret mounts\",\n                \"Audit logs retained for 18 months in cold storage\"\n            ]\n        },\n        \"bug_fixes_updates\": {\n            \"changelog\": [\n                \"[Fixed] Intermittent dashboard crash on bulk service imports\",\n                \"[Fixed] Incorrect latency display in metrics explorer\",\n                \"[Improved] Deployments now rollback automatically on failure\",\n                \"[Added] Optional OpenTelemetry tracing configuration\"\n            ],\n            \"known_issues\": [\n                \"Safari users may experience delayed chart rendering\",\n                \"Token refresh fails silently in rare edge cases (fix in 4.2.2)\",\n                \"nimbus plan CLI command underperforms on large YAML diffs\"\n            ]\n        },\n        \"key_dates_timelines\": {\n            \"software_release_update_schedules\": [\n                \"4.2.0 Stable Release: January 15, 2025\",\n                \"4.2.1 Patch Deployment: March 1, 2025\",\n                \"4.3.0 Beta Freeze: May 10, 2025\",\n                \"4.3.0 Beta Release: June 1, 2025\",\n                \"Next LTS (v5.0.0) Roadmap Draft: July 2025\",\n                \"Q2 Cybersecurity Patch: April 10, 2025\"\n            ],\n            \"API_deprecation_dates\": [\n                \"v2 API Deprecation Deadline: August 1, 2025\"\n            ],\n            \"cybersecurity_patch_release_dates\": []\n        }\n    }\n}"
  },
  "combined_approach": {
    "metrics": {
      "tokens": {
        "input": 5897,
        "output": 876,
        "total": 6773
      },
      "cost": 0.00094,
      "execution_time": 3.176170825958252
    },
    "result": "```json\n{\n    \"category\": \"IT_SOFTWARE\",\n    \"extracted_data\": {\n        \"software_info\": {\n            \"name\": \"Nimbus\",\n            \"version\": \"4.2.1\"\n        },\n        \"installation_setup\": {\n            \"steps\": [\n                \"curl -sSL https://nimbus.sh/install.sh | bash\",\n                \"Run post-install verification: nimbus check --all\",\n                \"Generate config scaffold: nimbus init\",\n                \"Edit nimbus.yaml for cluster-specific params\",\n                \"Use nimbus deploy to roll out the control plane\"\n            ],\n            \"configuration\": \"Environment Variables:\\nNIMBUS_ENV=production\\nNIMBUS_ENABLE_TLS=true\\nNIMBUS_API_KEY=[token]\\nDependencies:\\nDocker 23+\\nPython 3.10+\\nPostgres 14 (for internal logging)\"\n        },\n        \"user_interface_features\": {\n            \"functionalities\": [\n                \"Drag-and-drop service dependency mapping\",\n                \"Live mesh traffic inspection\",\n                \"Alerting & autoscaling rules\",\n                \"Inline YAML editor for resource definitions\",\n                \"Native integrations: GitHub, Datadog, PagerDuty\"\n            ],\n            \"shortcuts\": [\n                \"Ctrl+Shift+F \u2013 Toggle dark mode\",\n                \"Cmd+/ \u2013 Command palette\",\n                \"Esc \u2013 Collapse side navigation\",\n                \"/logs \u2013 Direct log stream via web\"\n            ],\n            \"compatibility\": \"Kubernetes 1.24\u20131.28\\nIstio 1.17+\\nTerraform integration supported via plugin\"\n        },\n        \"api_documentation\": {\n            \"endpoints\": [\n                \"GET /clusters/ \u2013 List registered clusters\",\n                \"POST /deployments/ \u2013 Create new deployment\",\n                \"GET /services/{id} \u2013 Get service metadata\",\n                \"DELETE /nodes/{id} \u2013 Evict node from pool\"\n            ],\n            \"authentication\": \"OAuth2 with Bearer tokens or API key header (X-Nimbus-Token)\",\n            \"code_examples\": \"python\\nCopy\\nEdit\\nimport requests\\n\\nheaders = {\\\"X-Nimbus-Token\\\": \\\"your_token_here\\\"}\\nresponse = requests.get(\\\"https://api.nimbus.sh/v1/clusters/\\\", headers=headers)\\nprint(response.json())\"\n        },\n        \"security_guidelines\": {\n            \"encryption\": \"TLS v1.3 enforced across all internal and external endpoints\\nPasswords hashed with Argon2id\\nAll logs shipped securely via Fluent Bit over gRPC\\nEncrypted volumes for audit logs (AES-256)\",\n            \"compliance_policies\": \"Admin privileges are scoped with RBAC + time-limited elevation (just-in-time access via Vault)\\nSecure Coding Standards: All PRs undergo static analysis (SonarCloud, Bandit)\\nNo hardcoded credentials; use secret mounts\\nAudit logs retained for 18 months in cold storage\"\n        },\n        \"bug_fixes_updates\": {\n            \"changelog\": \"[Fixed] Intermittent dashboard crash on bulk service imports\\n[Fixed] Incorrect latency display in metrics explorer\\n[Improved] Deployments now rollback automatically on failure\\n[Added] Optional OpenTelemetry tracing configuration\",\n            \"known_issues\": \"Safari users may experience delayed chart rendering\\nToken refresh fails silently in rare edge cases (fix in 4.2.2)\\nnimbus plan CLI command underperforms on large YAML diffs\"\n        },\n        \"key_dates_timelines\": {\n            \"software_release_update_schedules\": {\n                \"4.2.0 Stable Release\": \"January 15, 2025\",\n                \"4.2.1 Patch Deployment\": \"March 1, 2025\",\n                \"4.3.0 Beta Freeze\": \"May 10, 2025\",\n                \"4.3.0 Beta Release\": \"June 1, 2025\",\n                \"Next LTS (v5.0.0) Roadmap Draft\": \"July 2025\"\n            },\n            \"API_deprecation_dates\": \"v2 API Deprecation Deadline: August 1, 2025\",\n            \"cybersecurity_patch_release_dates\": \"Q2 Cybersecurity Patch: April 10, 2025\"\n        }\n    }\n}\n```"
  },
  "comparison": {
    "token_difference": -2759,
    "cost_difference": -0.000245,
    "cost_savings_percentage": -35.25179856115108,
    "time_difference": -0.01617908477783203,
    "time_savings_percentage": -0.5112338862634935
  }
}